README.md
bh100.py
setup.py
bh100.egg-info/PKG-INFO
bh100.egg-info/SOURCES.txt
bh100.egg-info/dependency_links.txt
bh100.egg-info/entry_points.txt
bh100.egg-info/requires.txt
bh100.egg-info/top_level.txt