Metadata-Version: 1.2
Name: bh100
Version: 1.0.1
Summary: Generates a JSON files of the top Crypto in the market and where you can buy them.
Home-page: https://github.com/rbn920/bh100
Author: Robert Nelson
Author-email: robertb.nelson@gmail.com
License: MIT
Platform: UNKNOWN
Requires-Python: >=3
